datashader_cli/__init__.py
datashader_cli/cli.py
datashader_cli/common.py
datashader_cli/datashader_cli.py
datashader_cli-0.0.4.dist-info/LICENSE
datashader_cli-0.0.4.dist-info/METADATA
datashader_cli-0.0.4.dist-info/WHEEL
datashader_cli-0.0.4.dist-info/dependency_links.txt
datashader_cli-0.0.4.dist-info/entry_points.txt
datashader_cli-0.0.4.dist-info/top_level.txt
datashader_cli-0.0.4.dist-info/RECORD
