Metadata-Version: 2.1
Name: datashader-cli
Version: 0.0.4
Summary: Quick visualization of large datasets using CLI based on datashader.
Home-page: https://github.com/wybert/datashader-cli
Author: Xiaokang Fu
Author-email: fxk123@gmail.com
License: MIT license
Keywords: datashader_cli
Classifier: Intended Audience :: Developers
Classifier: License :: OSI Approved :: MIT License
Classifier: Natural Language :: English
Classifier: Programming Language :: Python :: 3
Classifier: Programming Language :: Python :: 3.8
Classifier: Programming Language :: Python :: 3.9
Classifier: Programming Language :: Python :: 3.10
Classifier: Programming Language :: Python :: 3.11
Requires-Python: >=3.8
License-File: LICENSE
Requires-Dist: click
Requires-Dist: datashader
Requires-Dist: pandas
Requires-Dist: matplotlib
Requires-Dist: geopandas
Requires-Dist: pyarrow
